eprinttools/__init__.py
eprinttools/eprints3x/__init__.py
eprinttools/eprints3x/eprints.py
eprinttools/eprints3x/logger.py
eprinttools/eprints3x/mysql_access.py
eprinttools/eprints3x/s3_publisher.py
eprinttools/eprintviews/__init__.py
eprinttools/eprintviews/aggregator.py
eprinttools/eprintviews/config.py
eprinttools/eprintviews/frames.py
eprinttools/eprintviews/normalize.py
eprinttools/eprintviews/subjects.py
eprinttools/eprintviews/users.py
eprinttools/eprintviews/views.py
eprinttools-0.1.7.dist-info/LICENSE
eprinttools-0.1.7.dist-info/METADATA
eprinttools-0.1.7.dist-info/WHEEL
eprinttools-0.1.7.dist-info/top_level.txt
eprinttools-0.1.7.dist-info/RECORD
