Metadata-Version: 2.1
Name: eprinttools
Version: 0.1.7
Summary: Command line tools, Golang package and Python module for working with the EPrints 3.x REST API
Home-page: https://github.com/caltechlibrary/eprinttools
Author: Robert Doiel
Author-email: rsdoiel@caltech.edu
License: https://caltechlibrary.github.io/eprinttools/license.html
Download-URL: https://github.com/caltechlibrary/eprinttools/release/latest
Keywords: GitHub,metadata,repository,EPrints,CrossRef,DataCite,software
Platform: UNKNOWN
Classifier: Development Status :: 4 - Beta
Classifier: Environment :: Console
Classifier: Programming Language :: Python
Classifier: Programming Language :: Python :: 3
Classifier: Programming Language :: Other
Classifier: Intended Audience :: Science/Research
Classifier: Topic :: Scientific/Engineering
Classifier: License :: OSI Approved :: BSD License
Classifier: Operating System :: Microsoft :: Windows :: Windows 10
Classifier: Operating System :: POSIX :: Linux
Classifier: Operating System :: MacOS :: MacOS X
Requires-Python: >=3.7.0
Requires-Dist: py-dataset
